thursday/__init__.py
thursday/chrome.py
thursday/enums.py
thursday/exceptions.py
thursday-0.1a2.dist-info/LICENSE
thursday-0.1a2.dist-info/METADATA
thursday-0.1a2.dist-info/WHEEL
thursday-0.1a2.dist-info/top_level.txt
thursday-0.1a2.dist-info/RECORD
