Metadata-Version: 2.1
Name: thursday
Version: 0.1a2
Summary: Thursday reduces the time it takes to get up and running with Selenium.
License: GNU General Public License (GPL)
Classifier: Development Status :: 2 - Pre-Alpha
Classifier: Programming Language :: Python :: 3
Classifier: License :: OSI Approved :: GNU General Public License (GPL)
Classifier: Operating System :: Microsoft :: Windows
Requires-Python: >=3.7
License-File: LICENSE
Requires-Dist: requests
Requires-Dist: selenium
